ccc/__init__.py
ccc/draw.py
ccc/errors.py
ccc/multiset.py
ccc/partition.py
ccc/permutation.py
ccc/polynomialtracker.py
ccc/sequence.py
ccc/bin/__init__.py
ccc/bin/cli.py
ccc/commands/__init__.py
ccc/commands/count.py
ccc/commands/probability.py
ccc/util/__init__.py
ccc/util/collection.py
ccc/util/constraints.py
ccc/util/misc.py
ccc_calculator-0.1.0.dist-info/LICENSE
ccc_calculator-0.1.0.dist-info/METADATA
ccc_calculator-0.1.0.dist-info/WHEEL
ccc_calculator-0.1.0.dist-info/entry_points.txt
ccc_calculator-0.1.0.dist-info/top_level.txt
ccc_calculator-0.1.0.dist-info/RECORD
