Metadata-Version: 2.1
Name: ccc-calculator
Version: 0.1.0
Summary: command-line combinatorial calculator
Home-page: UNKNOWN
Author: Alex Riley
License: UNKNOWN
Project-URL: Source, https://github.com/ajcr/ccc/
Project-URL: Tracker, https://github.com/ajcr/ccc/issues
Keywords: count collection probability sequence permutation calculator
Platform: UNKNOWN
Classifier: Programming Language :: Python
Classifier: Programming Language :: Python :: 3
Classifier: Programming Language :: Python :: 3.6
Classifier: Programming Language :: Python :: 3.7
Classifier: Programming Language :: Python :: 3.8
Requires-Python: >=3.6.0
Requires-Dist: sympy
Requires-Dist: click
